instrumental_dl/__init__.py
instrumental_dl/__main__.py
instrumental_dl/__version__.py
instrumental_dl/args.py
instrumental_dl/client.py
instrumental_dl/conversion.py
instrumental_dl/exceptions.py
instrumental_dl/file_input.py
instrumental_dl/file_names.py
instrumental_dl/main.py
instrumental_dl/youtube_dl_wrapper.py
instrumental_dl-0.6.5.data/data/config/arg_help.json
instrumental_dl-0.6.5.data/data/config/keywords
instrumental_dl-0.6.5.data/data/config/logging.conf
instrumental_dl-0.6.5.dist-info/LICENSE
instrumental_dl-0.6.5.dist-info/METADATA
instrumental_dl-0.6.5.dist-info/WHEEL
instrumental_dl-0.6.5.dist-info/entry_points.txt
instrumental_dl-0.6.5.dist-info/top_level.txt
instrumental_dl-0.6.5.dist-info/RECORD
