Metadata-Version: 2.1
Name: instrumental-dl
Version: 0.6.5
Summary: A command line tool to easily download song instrumentals from Youtube.
Home-page: https://github.com/QualityHammer/instrumental-downloader
Author: QualityHammer
Author-email: agingllama@gmail.com
License: UNKNOWN
Platform: UNKNOWN
Classifier: Programming Language :: Python :: 3
Classifier: License :: OSI Approved :: MIT License
Classifier: Operating System :: OS Independent
Requires-Python: >=3.6
Requires-Dist: youtube-dl (>=2020.2.16)
